listele/__init__.py
listele/listele.py
listele_esat_cpu-0.0.1.dist-info/licenses/LICENSE
listele_esat_cpu-0.0.1.dist-info/METADATA
listele_esat_cpu-0.0.1.dist-info/WHEEL
listele_esat_cpu-0.0.1.dist-info/top_level.txt
listele_esat_cpu-0.0.1.dist-info/RECORD
