Metadata-Version: 2.4
Name: listele_Esat-cpu
Version: 0.0.1
Summary: Just a printing listed version function.
Author-email: Esat Saygın <saygina7@gmail.com>
License-Expression: MIT
Project-URL: Homepage, https://github.com/Esat-cpu/listele
Project-URL: Issues, https://github.com/Esat-cpu/listele/issues
Classifier: Programming Language :: Python :: 3
Classifier: Operating System :: OS Independent
Requires-Python: >=3.9
License-File: LICENSE
Dynamic: license-file
